ezx_pyapi-1.1.2.dist-info/licenses/LICENSE.txt
iserver/EzxMsg.py
iserver/__init__.py
iserver/ezx_msg.py
iserver/msg_factory.py
iserver/net.py
iserver/util.py
iserver/enums/__init__.py
iserver/enums/api.py
iserver/enums/msgenums.py
iserver/msgs/AccountInfo.py
iserver/msgs/AdminCommand.py
iserver/msgs/AdminResponse.py
iserver/msgs/AllocAccountInfo.py
iserver/msgs/AllocInfo.py
iserver/msgs/AllocationInfoRequest.py
iserver/msgs/AllocationInfoResponse.py
iserver/msgs/AllocationRequest.py
iserver/msgs/AllocationRequestInfo.py
iserver/msgs/AllocationRequestStatus.py
iserver/msgs/AllocationResponse.py
iserver/msgs/AllocationStatus.py
iserver/msgs/BondExecutionStatus.py
iserver/msgs/Broadcast.py
iserver/msgs/BroadcastResponse.py
iserver/msgs/CancelAll.py
iserver/msgs/ChangePasswordRequest.py
iserver/msgs/ChangePasswordResponse.py
iserver/msgs/ChoiceGroup.py
iserver/msgs/ChoiceItem.py
iserver/msgs/ClientOrderRequest.py
iserver/msgs/ClientOrderRequestInfo.py
iserver/msgs/ClientOrderResponse.py
iserver/msgs/ClientOrderStatus.py
iserver/msgs/ClientSettingsUpdate.py
iserver/msgs/CompanySettingsUpdate.py
iserver/msgs/CreateGroupAccount.py
iserver/msgs/CreditUsedUpdate.py
iserver/msgs/DeleteAccount.py
iserver/msgs/DeleteClientOrder.py
iserver/msgs/DeleteGroup.py
iserver/msgs/Destination.py
iserver/msgs/DestinationStatus.py
iserver/msgs/EngineStatus.py
iserver/msgs/ExecutionRequest.py
iserver/msgs/ExecutionResponse.py
iserver/msgs/ExecutionStatus.py
iserver/msgs/FixedIncomeMarketDataIncrementalRefresh.py
iserver/msgs/ForgotPasswordRequest.py
iserver/msgs/ForgotPasswordResponse.py
iserver/msgs/GetOrdersRequest.py
iserver/msgs/GetOrdersResponse.py
iserver/msgs/GroupAccount.py
iserver/msgs/GroupAccountChange.py
iserver/msgs/HeartBeatMsg.py
iserver/msgs/IOI.py
iserver/msgs/IncrementalMdEntries.py
iserver/msgs/LogonRequest.py
iserver/msgs/LogonResponse.py
iserver/msgs/Logout.py
iserver/msgs/MarketDataHealthMessage.py
iserver/msgs/MarketDataIncremental.py
iserver/msgs/MarketDataSnapshot.py
iserver/msgs/MoveAccount.py
ezx_pyapi-1.1.2.dist-info/METADATA
ezx_pyapi-1.1.2.dist-info/WHEEL
ezx_pyapi-1.1.2.dist-info/top_level.txt
ezx_pyapi-1.1.2.dist-info/RECORD
