Metadata-Version: 2.4
Name: ezx-pyapi
Version: 1.1.2
Summary: EZX API client and message library for communicating with the iServer.
Home-page: https://www.ezxinc.com/
Author: EZX Inc.
Author-email: support@ezxinc.com
License: MIT
Project-URL: Sample API Application, https://github.com/EZXInc/ezx-sample-py
Project-URL: Documentation, https://github.com/EZXInc/ezx-sample-py/wiki
Project-URL: Change Log, https://github.com/EZXInc/ezx-sample-py/blob/master/CHANGELOG-API.md
Keywords: EZX iServer API trading
Classifier: Programming Language :: Python :: 3.8
Classifier: Programming Language :: Python :: 3.9
Classifier: Programming Language :: Python :: 3.10
Classifier: Programming Language :: Python :: 3.11
Classifier: License :: OSI Approved :: MIT License
Classifier: Operating System :: OS Independent
Requires-Python: >=3.8, <4
License-File: LICENSE.txt
Dynamic: author
Dynamic: author-email
Dynamic: classifier
Dynamic: description
Dynamic: description-content-type
Dynamic: home-page
Dynamic: keywords
Dynamic: license
Dynamic: license-file
Dynamic: project-url
Dynamic: requires-python
Dynamic: summary
